{
    "key": "venue",
    "name": "Venue",
    "description": "We're getting married on November 2nd, 2019 at Syndicated in Brooklyn, NY! Visit our wedding website to RSVP online, view pictures, get directions, and more.",
    "robots": "index,follow",
    "navigation": [
        {
            "name": "Home",
            "path": "/",
            "active": false
        },
        {
            "name": "RSVP",
            "path": "/rsvp",
            "active": false
        },
        {
            "name": "Venue",
            "path": "/venue",
            "active": true
        },
        {
            "name": "Travel",
            "path": "/travel",
            "active": false
        }
    ]
}
